pyxmv/__init__.py
pyxmv/app.py
pyxmv/cli.py
pyxmv/outcome.py
pyxmv/pyxmv.py
pyxmv/simulation_heuristics.py
pyxmv/utils.py
pyxmv-0.6.0.dist-info/LICENSE
pyxmv-0.6.0.dist-info/METADATA
pyxmv-0.6.0.dist-info/WHEEL
pyxmv-0.6.0.dist-info/entry_points.txt
pyxmv-0.6.0.dist-info/RECORD
